asyncio_micro.py
setup.py
micropython_asyncio_micro.egg-info/PKG-INFO
micropython_asyncio_micro.egg-info/SOURCES.txt
micropython_asyncio_micro.egg-info/dependency_links.txt
micropython_asyncio_micro.egg-info/requires.txt
micropython_asyncio_micro.egg-info/top_level.txt