Metadata-Version: 1.0
Name: micropython-asyncio-micro
Version: 0.5
Summary: asyncio_micro module for MicroPython
Home-page: https://github.com/micropython/micropython/issues/405
Author: MicroPython Developers
Author-email: micro-python@googlegroups.com
License: MIT
Platform: UNKNOWN
